odoo/addons/hr_branch/README.rst
odoo/addons/hr_branch/__init__.py
odoo/addons/hr_branch/__manifest__.py
odoo/addons/hr_branch/i18n/es.po
odoo/addons/hr_branch/i18n/hr_branch.pot
odoo/addons/hr_branch/models/__init__.py
odoo/addons/hr_branch/models/hr_department.py
odoo/addons/hr_branch/readme/CONTRIBUTORS.rst
odoo/addons/hr_branch/readme/DESCRIPTION.rst
odoo/addons/hr_branch/static/description/icon.png
odoo/addons/hr_branch/static/description/index.html
odoo/addons/hr_branch/views/hr_department_views.xml
odoo/addons/hr_branch/views/hr_employee_views.xml
odoo13_addon_hr_branch-13.0.1.0.1.dist-info/METADATA
odoo13_addon_hr_branch-13.0.1.0.1.dist-info/WHEEL
odoo13_addon_hr_branch-13.0.1.0.1.dist-info/top_level.txt
odoo13_addon_hr_branch-13.0.1.0.1.dist-info/RECORD
