Metadata-Version: 2.1
Name: odoo13-addon-hr-branch
Version: 13.0.1.0.1
Summary: Allow define company branch for employee process
Home-page: https://github.com/OCA/hr
Author: Vauxoo, Odoo Community Association (OCA)
Author-email: support@odoo-community.org
License: LGPL-3
Platform: UNKNOWN
Classifier: Programming Language :: Python
Classifier: Framework :: Odoo
Classifier: License :: OSI Approved :: GNU Lesser General Public License v3 (LGPLv3)
Classifier: Development Status :: 6 - Mature
Requires-Python: >=3.5
Requires-Dist: odoo (<13.1dev,>=13.0a)
